text_toolkit/__init__.py
text_toolkit/core.py
text_manipulation-0.1.0.dist-info/LICENSE
text_manipulation-0.1.0.dist-info/METADATA
text_manipulation-0.1.0.dist-info/WHEEL
text_manipulation-0.1.0.dist-info/top_level.txt
text_manipulation-0.1.0.dist-info/RECORD
