Metadata-Version: 2.1
Name: text_manipulation
Version: 0.1.0
Summary: Un package Python pour la manipulation de texte
Home-page: https://github.com/Zakiyou/text_toolkit.git
Author: Ton Nom
Author-email: zakiyoubababodi@gmail.com
Classifier: Programming Language :: Python :: 3
Classifier: License :: OSI Approved :: MIT License
Classifier: Operating System :: OS Independent
Requires-Python: >=3.6
License-File: LICENSE
